LICENSE
README.md
setup.cfg
setup.py
digitaloceanobjects/__init__.py
digitaloceanobjects.egg-info/PKG-INFO
digitaloceanobjects.egg-info/SOURCES.txt
digitaloceanobjects.egg-info/dependency_links.txt
digitaloceanobjects.egg-info/requires.txt
digitaloceanobjects.egg-info/top_level.txt
digitaloceanobjects/common/__init__.py
digitaloceanobjects/common/cloudapiexceptions.py
digitaloceanobjects/digitaloceanapi/__init__.py
digitaloceanobjects/digitaloceanapi/accounts.py
digitaloceanobjects/digitaloceanapi/actions.py
digitaloceanobjects/digitaloceanapi/digitaloceanapiconnection.py
digitaloceanobjects/digitaloceanapi/droplets.py
digitaloceanobjects/digitaloceanapi/floatingips.py
digitaloceanobjects/digitaloceanapi/regions.py
digitaloceanobjects/digitaloceanapi/sizes.py
digitaloceanobjects/digitaloceanapi/snapshots.py
digitaloceanobjects/digitaloceanapi/sshkeys.py
digitaloceanobjects/digitaloceanapi/volumes.py
digitaloceanobjects/digitaloceanobject/__init__.py
digitaloceanobjects/digitaloceanobject/account.py
digitaloceanobjects/digitaloceanobject/action.py
digitaloceanobjects/digitaloceanobject/droplet.py
digitaloceanobjects/digitaloceanobject/floatingip.py
digitaloceanobjects/digitaloceanobject/region.py
digitaloceanobjects/digitaloceanobject/size.py
digitaloceanobjects/digitaloceanobject/snapshot.py
digitaloceanobjects/digitaloceanobject/sshkey.py
digitaloceanobjects/digitaloceanobject/volume.py