Metadata-Version: 2.1
Name: digitaloceanobjects
Version: 0.0.22
Summary: digitaloceanobjects, represents all digital ocean services as objects, hiding all those horrible api calls.
Home-page: https://github.com/zorani/digitalocean-objects
Download-URL: https://github.com/zorani/digitalocean-objects/archive/refs/tags/v0.0.22.tar.gz
Author: zoran ilievski
Author-email: pythonic@clientuser.net
License: MIT
Keywords: digitalocean,api,objects,digitaloceanapi
Classifier: Development Status :: 4 - Beta
Classifier: Intended Audience :: Developers
Classifier: Topic :: Software Development :: Libraries :: Python Modules
Classifier: Topic :: Internet :: WWW/HTTP :: HTTP Servers
Classifier: Operating System :: POSIX :: Linux
Classifier: License :: OSI Approved :: MIT License
Classifier: Programming Language :: Python :: 3.7
Classifier: Programming Language :: Python :: 3.8
Classifier: Programming Language :: Python :: 3.9
License-File: LICENSE
